thousandeyes_sdk/test_results/__init__.py
thousandeyes_sdk/test_results/py.typed
thousandeyes_sdk/test_results/api/__init__.py
thousandeyes_sdk/test_results/api/api_test_results_api.py
thousandeyes_sdk/test_results/api/dns_server_test_results_api.py
thousandeyes_sdk/test_results/api/dns_trace_test_results_api.py
thousandeyes_sdk/test_results/api/dnssec_test_results_api.py
thousandeyes_sdk/test_results/api/network_bgp_test_results_api.py
thousandeyes_sdk/test_results/api/network_test_results_api.py
thousandeyes_sdk/test_results/api/voice_rtp_server_test_results_api.py
thousandeyes_sdk/test_results/api/voice_sip_server_test_results_api.py
thousandeyes_sdk/test_results/api/web_ftp_server_test_results_api.py
thousandeyes_sdk/test_results/api/web_http_server_test_results_api.py
thousandeyes_sdk/test_results/api/web_page_load_test_results_api.py
thousandeyes_sdk/test_results/api/web_transactions_test_results_api.py
thousandeyes_sdk/test_results/models/__init__.py
thousandeyes_sdk/test_results/models/api_detail_test_result.py
thousandeyes_sdk/test_results/models/api_detail_test_results.py
thousandeyes_sdk/test_results/models/api_request_detail.py
thousandeyes_sdk/test_results/models/api_request_detail_assertion.py
thousandeyes_sdk/test_results/models/api_request_step_type.py
thousandeyes_sdk/test_results/models/api_test_result.py
thousandeyes_sdk/test_results/models/api_test_results.py
thousandeyes_sdk/test_results/models/app_links.py
thousandeyes_sdk/test_results/models/bgp_basic_test_result.py
thousandeyes_sdk/test_results/models/bgp_hop.py
thousandeyes_sdk/test_results/models/bgp_test_result.py
thousandeyes_sdk/test_results/models/bgp_test_results.py
thousandeyes_sdk/test_results/models/bgp_test_route_information_result.py
thousandeyes_sdk/test_results/models/bgp_test_route_information_results.py
thousandeyes_sdk/test_results/models/dns_server_test_result.py
thousandeyes_sdk/test_results/models/dns_server_test_results.py
thousandeyes_sdk_test_results-2.23.0.dist-info/licenses/LICENSE
thousandeyes_sdk_test_results-2.23.0.dist-info/licenses/NOTICE
thousandeyes_sdk_test_results-2.23.0.dist-info/METADATA
thousandeyes_sdk_test_results-2.23.0.dist-info/WHEEL
thousandeyes_sdk_test_results-2.23.0.dist-info/top_level.txt
thousandeyes_sdk_test_results-2.23.0.dist-info/RECORD
